trying_verilog/test.v
module counter (
    input clk,
    input rst,
    output reg [3:0] count
);

always @(posedge clk or posedge rst) begin
    if (rst)
        count <= 4'b0000;
    else
        count <= count + 1;
end

endmodule

trying_verilog/testbench.v
`timescale 1ns/1ps

module testbench;
    reg clk, rst;
    wire [3:0] count;

    // Instantiate the counter
    counter uut (
        .clk(clk),
        .rst(rst),
        .count(count)
    );

    // Clock generation
    always #5 clk = ~clk; // 10ns period

    initial begin
        $dumpfile("counter.vcd");
        $dumpvars(0, testbench);

        clk = 0;
        rst = 1;  // Reset the counter
        #10 rst = 0; // Release reset
        
        #100; // Run simulation for 100ns
        $finish;
    end
endmodule

trying_verilog/counter.vcd
$date
	Fri Mar  7 19:49:26 2025
$end
$version
	Icarus Verilog
$end
$timescale
	1ps
$end
$scope module testbench $end
$var wire 4 ! count [3:0] $end
$var reg 1 " clk $end
$var reg 1 # rst $end
$scope module uut $end
$var wire 1 " clk $end
$var wire 1 # rst $end
$var reg 4 $ count [3:0] $end
$upscope $end
$upscope $end
$enddefinitions $end
$comment Show the parameter values. $end
$dumpall
$end
#0
$dumpvars
b0 $
1#
0"
b0 !
$end
#5000
1"
#10000
0"
0#
#15000
b1 !
b1 $
1"
#20000
0"
#25000
b10 !
b10 $
1"
#30000
0"
#35000
b11 !
b11 $
1"
#40000
0"
#45000
b100 !
b100 $
1"
#50000
0"
#55000
b101 !
b101 $
1"
#60000
0"
#65000
b110 !
b110 $
1"
#70000
0"
#75000
b111 !
b111 $
1"
#80000
0"
#85000
b1000 !
b1000 $
1"
#90000
0"
#95000
b1001 !
b1001 $
1"
#100000
0"
#105000
b1010 !
b1010 $
1"
