project_2/full_adder/full_adder.v
// owner:virajitgp; a verilog imp of a full adder with basic gates

module FullAdder(
    input a, b, cin,
    output sum, cout
);
    // Internal wires
    wire w1, w2, w3, w4;
    
    // Sum is XOR of a, b, and cin
    xor(w1, a, b);
    xor(sum, w1, cin);
    
    // Carry out calculation
    and(w2, a, b);    // a AND b
    and(w3, a, cin);  // a AND cin
    and(w4, b, cin);  // b AND cin
    
    // Carry out is OR of all partial carries
    or(cout, w2, w3, w4);
endmodule

project_2/full_adder/full_adder-test.v
`timescale 1ns/1ps

module FullAdder_tb();
    // Inputs
    reg a, b, cin;
    
    // Outputs
    wire sum, cout;
    
    // Instantiate the Unit Under Test (UUT)
    FullAdder uut (
        .a(a),
        .b(b),
        .cin(cin),
        .sum(sum),
        .cout(cout)
    );
    
    // For GTKWave
    initial begin
        $dumpfile("full_adder.vcd");
        $dumpvars(0, FullAdder_tb);
    end
    
    // Test sequence
    initial begin
        // Initialize inputs
        a = 0; b = 0; cin = 0;
        #10;
        
        a = 0; b = 0; cin = 1;
        #10;
        
        a = 0; b = 1; cin = 0;
        #10;
        
        a = 0; b = 1; cin = 1;
        #10;
        
        a = 1; b = 0; cin = 0;
        #10;
        
        a = 1; b = 0; cin = 1;
        #10;
        
        a = 1; b = 1; cin = 0;
        #10;
        
        a = 1; b = 1; cin = 1;
        #10;
        
        // End simulation
        $finish;
    end
    
    // Monitor changes
    initial begin
        $monitor("Time = %0t: a = %b, b = %b, cin = %b, sum = %b, cout = %b", 
                 $time, a, b, cin, sum, cout);
    end
endmodule

project_2/full_adder/full_adder.vcd
$date
	Tue Mar 18 19:20:27 2025
$end
$version
	Icarus Verilog
$end
$timescale
	1ps
$end
$scope module FullAdder_tb $end
$var wire 1 ! sum $end
$var wire 1 " cout $end
$var reg 1 # a $end
$var reg 1 $ b $end
$var reg 1 % cin $end
$scope module uut $end
$var wire 1 # a $end
$var wire 1 $ b $end
$var wire 1 % cin $end
$var wire 1 " cout $end
$var wire 1 ! sum $end
$var wire 1 & w1 $end
$var wire 1 ' w2 $end
$var wire 1 ( w3 $end
$var wire 1 ) w4 $end
$upscope $end
$upscope $end
$enddefinitions $end
$comment Show the parameter values. $end
$dumpall
$end
#0
$dumpvars
0)
0(
0'
0&
0%
0$
0#
0"
0!
$end
#10000
1!
1%
#20000
1&
0%
1$
#30000
1"
0!
1)
1%
#40000
0"
1!
0)
0%
0$
1#
#50000
1"
0!
1(
1%
#60000
0(
0&
1'
0%
1$
#70000
1!
1(
1)
1%
