project_2/alu/alu.v
module alu(
    input [15:0] a,        // 16-bit input operand A
    input [15:0] b,        // 16-bit input operand B
    input [3:0] op_code,   // 4-bit operation code
    output reg [15:0] result,  // 16-bit output result
    output reg zero_flag,      // Set when result is zero
    output reg carry_flag,     // Set when operation produces a carry
    output reg overflow_flag   // Set when operation produces an overflow
);

    // Operation codes
    parameter ADD = 4'b0000;   // Addition
    parameter SUB = 4'b0001;   // Subtraction
    parameter AND = 4'b0010;   // Bitwise AND
    parameter OR  = 4'b0011;   // Bitwise OR
    parameter XOR = 4'b0100;   // Bitwise XOR
    parameter NOT = 4'b0101;   // Bitwise NOT (of operand A)
    parameter SHL = 4'b0110;   // Shift left A by B bits
    parameter SHR = 4'b0111;   // Shift right A by B bits
    parameter CMPEQ = 4'b1000; // Compare equal
    parameter CMPLT = 4'b1001; // Compare less than
    parameter CMPLE = 4'b1010; // Compare less than or equal
    parameter MUL = 4'b1011;   // Multiplication

    // Temporary variables for calculations
    reg [16:0] temp;       // 17-bit temp for carry detection
    reg [31:0] mul_temp;   // 32-bit temp for multiplication

    always @(*) begin
        // Default flag values
        zero_flag = 0;
        carry_flag = 0;
        overflow_flag = 0;
        
        case(op_code)
            ADD: begin
                temp = a + b;
                result = temp[15:0];
                carry_flag = temp[16];
                // Overflow occurs when adding two numbers of the same sign
                // and the result has a different sign
                overflow_flag = (a[15] == b[15]) && (result[15] != a[15]);
            end
            
            SUB: begin
                temp = a - b;
                result = temp[15:0];
                carry_flag = temp[16];
                // Overflow occurs when subtracting numbers of different signs
                // and the result has a different sign than the first operand
                overflow_flag = (a[15] != b[15]) && (result[15] != a[15]);
            end
            
            AND: begin
                result = a & b;
            end
            
            OR: begin
                result = a | b;
            end
            
            XOR: begin
                result = a ^ b;
            end
            
            NOT: begin
                result = ~a;
            end
            
            SHL: begin
                result = a << b[3:0]; // Use only lower 4 bits of B for shift amount (max 16 positions)
                // Carry is the last bit shifted out
                if (b[3:0] > 0)
                    carry_flag = (b[3:0] > 15) ? 0 : a[16-b[3:0]];
            end
            
            SHR: begin
                result = a >> b[3:0]; // Use only lower 4 bits of B for shift amount (max 16 positions)
                // Carry is the last bit shifted out
                if (b[3:0] > 0)
                    carry_flag = (b[3:0] > 15) ? 0 : a[b[3:0]-1];
            end
            
            CMPEQ: begin
                result = (a == b) ? 16'h0001 : 16'h0000;
            end
            
            CMPLT: begin
                result = ($signed(a) < $signed(b)) ? 16'h0001 : 16'h0000;
            end
            
            CMPLE: begin
                result = ($signed(a) <= $signed(b)) ? 16'h0001 : 16'h0000;
            end
            
            MUL: begin
                mul_temp = a * b;
                result = mul_temp[15:0];
                // Carry flag if upper bits are non-zero
                carry_flag = |mul_temp[31:16];
                // No defined overflow for multiplication in this ALU
            end
            
            default: begin
                result = 16'h0000;
            end
        endcase
        
        // Set zero flag if result is zero
        zero_flag = (result == 16'h0000);
    end

endmodule

project_2/alu/alu-test.v
`timescale 1ns/1ps

module alu_tb();
    // Test signals
    reg [15:0] a;
    reg [15:0] b;
    reg [3:0] op_code;
    wire [15:0] result;
    wire zero_flag;
    wire carry_flag;
    wire overflow_flag;
    
    // Instantiate the ALU
    alu dut(
        .a(a),
        .b(b),
        .op_code(op_code),
        .result(result),
        .zero_flag(zero_flag),
        .carry_flag(carry_flag),
        .overflow_flag(overflow_flag)
    );
    
    // Helper tasks
    task display_result;
        input [15:0] expected_result;
        input expected_zero;
        input expected_carry;
        input expected_overflow;
        begin
            #1; // Wait for signals to propagate
            
            $display("Operation: %b, A: %d, B: %d", op_code, a, b);
            $display("Result: %d (Expected: %d)", result, expected_result);
            $display("Zero Flag: %b (Expected: %b)", zero_flag, expected_zero);
            $display("Carry Flag: %b (Expected: %b)", carry_flag, expected_carry);
            $display("Overflow Flag: %b (Expected: %b)", overflow_flag, expected_overflow);
            
            if (result !== expected_result || zero_flag !== expected_zero || 
                carry_flag !== expected_carry || overflow_flag !== expected_overflow) begin
                $display("TEST FAILED!");
            end else begin
                $display("Test passed.");
            end
            
            $display("---------------------------");
        end
    endtask
    
    // Test stimulus
    initial begin
        $display("Starting 16-bit ALU Testbench");
        
        // Test addition
        a = 16'd1000; b = 16'd2000; op_code = 4'b0000;
        #10 display_result(16'd3000, 0, 0, 0);
        
        // Test addition with carry
        a = 16'd40000; b = 16'd30000; op_code = 4'b0000;
        #10 display_result(16'd4464, 0, 1, 0); // 70000 % 65536 = 4464, with carry
        
        // Test addition with overflow
        a = 16'h7FFF; b = 16'h0001; op_code = 4'b0000; // 32767 + 1 = 32768 (overflow)
        #10 display_result(16'h8000, 0, 0, 1);
        
        // Test subtraction
        a = 16'd5000; b = 16'd2000; op_code = 4'b0001;
        #10 display_result(16'd3000, 0, 0, 0);
        
        // Test subtraction with borrow
        a = 16'd1000; b = 16'd2000; op_code = 4'b0001;
        #10 display_result(16'd64536, 0, 1, 0); // -1000 = 64536 in two's complement
        
        // Test subtraction with overflow
        a = 16'h8000; b = 16'h0001; op_code = 4'b0001; // -32768 - 1 = -32769 (overflow)
        #10 display_result(16'h7FFF, 0, 1, 1);
        
        // Test logical operations
        a = 16'hAAAA; b = 16'h5555; op_code = 4'b0010; // AND
        #10 display_result(16'h0000, 1, 0, 0);
        
        a = 16'hAAAA; b = 16'h5555; op_code = 4'b0011; // OR
        #10 display_result(16'hFFFF, 0, 0, 0);
        
        a = 16'hAAAA; b = 16'h5555; op_code = 4'b0100; // XOR
        #10 display_result(16'hFFFF, 0, 0, 0);
        
        a = 16'hAAAA; b = 16'h0000; op_code = 4'b0101; // NOT
        #10 display_result(16'h5555, 0, 0, 0);
        
        // Test shifts
        a = 16'h0001; b = 16'h0008; op_code = 4'b0110; // SHL
        #10 display_result(16'h0100, 0, 0, 0);
        
        a = 16'h8000; b = 16'h0008; op_code = 4'b0111; // SHR
        #10 display_result(16'h0080, 0, 0, 0);
        
        // Test comparisons
        a = 16'd1000; b = 16'd1000; op_code = 4'b1000; // CMPEQ
        #10 display_result(16'h0001, 0, 0, 0);
        
        a = 16'd500; b = 16'd1000; op_code = 4'b1001; // CMPLT
        #10 display_result(16'h0001, 0, 0, 0);
        
        a = 16'd1000; b = 16'd1000; op_code = 4'b1010; // CMPLE
        #10 display_result(16'h0001, 0, 0, 0);
        
        // Test multiplication
        a = 16'd100; b = 16'd50; op_code = 4'b1011; // MUL
        #10 display_result(16'd5000, 0, 0, 0);
        
        a = 16'd1000; b = 16'd1000; op_code = 4'b1011; // MUL with carry
        #10 display_result(16'd16960, 0, 1, 0); // 1000000 % 65536 = 16960, with carry
        
        $display("16-bit ALU Testbench Complete");
        $finish;
    end
    
    // GTKWave dump
    initial begin
        $dumpfile("alu_tb.vcd");
        $dumpvars(0, alu_tb);
    end

endmodule

project_2/alu/alu_tb.vcd
$date
	Sun Mar 23 00:18:21 2025
$end
$version
	Icarus Verilog
$end
$timescale
	1ps
$end
$scope module alu_tb $end
$var wire 1 ! zero_flag $end
$var wire 16 " result [15:0] $end
$var wire 1 # overflow_flag $end
$var wire 1 $ carry_flag $end
$var reg 16 % a [15:0] $end
$var reg 16 & b [15:0] $end
$var reg 4 ' op_code [3:0] $end
$scope module dut $end
$var wire 16 ( a [15:0] $end
$var wire 16 ) b [15:0] $end
$var wire 4 * op_code [3:0] $end
$var parameter 4 + ADD $end
$var parameter 4 , AND $end
$var parameter 4 - CMPEQ $end
$var parameter 4 . CMPLE $end
$var parameter 4 / CMPLT $end
$var parameter 4 0 MUL $end
$var parameter 4 1 NOT $end
$var parameter 4 2 OR $end
$var parameter 4 3 SHL $end
$var parameter 4 4 SHR $end
$var parameter 4 5 SUB $end
$var parameter 4 6 XOR $end
$var reg 1 $ carry_flag $end
$var reg 32 7 mul_temp [31:0] $end
$var reg 1 # overflow_flag $end
$var reg 16 8 result [15:0] $end
$var reg 17 9 temp [16:0] $end
$var reg 1 ! zero_flag $end
$upscope $end
$scope task display_result $end
$var reg 1 : expected_carry $end
$var reg 1 ; expected_overflow $end
$var reg 16 < expected_result [15:0] $end
$var reg 1 = expected_zero $end
$upscope $end
$upscope $end
$enddefinitions $end
$comment Show the parameter values. $end
$dumpall
b100 6
b1 5
b111 4
b110 3
b11 2
b101 1
b1011 0
b1001 /
b1010 .
b1000 -
b10 ,
b0 +
$end
#0
$dumpvars
x=
bx <
x;
x:
b101110111000 9
b101110111000 8
bx 7
b0 *
b11111010000 )
b1111101000 (
b0 '
b11111010000 &
b1111101000 %
0$
0#
b101110111000 "
0!
$end
#10000
0;
0:
0=
b101110111000 <
#11000
1$
b1000101110000 "
b1000101110000 8
b10001000101110000 9
b111010100110000 &
b111010100110000 )
b1001110001000000 %
b1001110001000000 (
#21000
1:
b1000101110000 <
#22000
1#
b1000000000000000 "
b1000000000000000 8
b1000000000000000 9
0$
b1 &
b1 )
b111111111111111 %
b111111111111111 (
#32000
1;
0:
b1000000000000000 <
#33000
b101110111000 "
b101110111000 8
b101110111000 9
0#
b1 '
b1 *
b11111010000 &
b11111010000 )
b1001110001000 %
b1001110001000 (
#43000
0;
b101110111000 <
#44000
1$
b1111110000011000 "
b1111110000011000 8
b11111110000011000 9
b1111101000 %
b1111101000 (
#54000
1:
b1111110000011000 <
#55000
1#
b111111111111111 "
b111111111111111 8
b111111111111111 9
0$
b1 &
b1 )
b1000000000000000 %
b1000000000000000 (
#65000
1;
b111111111111111 <
#66000
1!
b0 "
b0 8
0#
b10 '
b10 *
b101010101010101 &
b101010101010101 )
b1010101010101010 %
b1010101010101010 (
#76000
0;
0:
1=
b0 <
#77000
b1111111111111111 "
b1111111111111111 8
0!
b11 '
b11 *
#87000
0=
b1111111111111111 <
#88000
b100 '
b100 *
#99000
b101010101010101 "
b101010101010101 8
b101 '
b101 *
b0 &
b0 )
#109000
b101010101010101 <
#110000
b100000000 "
b100000000 8
b110 '
b110 *
b1000 &
b1000 )
b1 %
b1 (
#120000
b100000000 <
#121000
b10000000 "
b10000000 8
b111 '
b111 *
b1000000000000000 %
b1000000000000000 (
#131000
b10000000 <
#132000
b1 "
b1 8
b1000 '
b1000 *
b1111101000 &
b1111101000 )
b1111101000 %
b1111101000 (
#142000
b1 <
#143000
b1001 '
b1001 *
b111110100 %
b111110100 (
#154000
b1010 '
b1010 *
b1111101000 %
b1111101000 (
#165000
b1001110001000 "
b1001110001000 8
b1001110001000 7
b1011 '
b1011 *
b110010 &
b110010 )
b1100100 %
b1100100 (
#175000
b1001110001000 <
#176000
1$
b100001001000000 "
b100001001000000 8
b11110100001001000000 7
b1111101000 &
b1111101000 )
b1111101000 %
b1111101000 (
#186000
1:
b100001001000000 <
