project_2/alu/alu.v
// owner: virajitgp; ALU behavioral verilog
module alu(
    input [7:0] a,         // 8-bit input operand A
    input [7:0] b,         // 8-bit input operand B
    input [3:0] op_code,   // 4-bit operation code
    output reg [7:0] result,   // 8-bit output result
    output reg zero_flag,      // Set when result is zero
    output reg carry_flag,     // Set when operation produces a carry
    output reg overflow_flag   // Set when operation produces an overflow
);

    // Operation codes
    parameter ADD = 4'b0000;   // Addition
    parameter SUB = 4'b0001;   // Subtraction
    parameter AND = 4'b0010;   // Bitwise AND
    parameter OR  = 4'b0011;   // Bitwise OR
    parameter XOR = 4'b0100;   // Bitwise XOR
    parameter NOT = 4'b0101;   // Bitwise NOT (of operand A)
    parameter SHL = 4'b0110;   // Shift left A by B bits
    parameter SHR = 4'b0111;   // Shift right A by B bits
    parameter CMPEQ = 4'b1000; // Compare equal
    parameter CMPLT = 4'b1001; // Compare less than
    parameter CMPLE = 4'b1010; // Compare less than or equal
    parameter MUL = 4'b1011;   // Multiplication

    // Temporary variables for calculations
    reg [8:0] temp;    // 9-bit temp for carry detection
    reg [15:0] mul_temp; // 16-bit temp for multiplication

    always @(*) begin
        // Default flag values
        zero_flag = 0;
        carry_flag = 0;
        overflow_flag = 0;
        
        case(op_code)
            ADD: begin
                temp = a + b;
                result = temp[7:0];
                carry_flag = temp[8];
                // Overflow occurs when adding two numbers of the same sign
                // and the result has a different sign
                overflow_flag = (a[7] == b[7]) && (result[7] != a[7]);
            end
            
            SUB: begin
                temp = a - b;
                result = temp[7:0];
                carry_flag = temp[8];
                // Overflow occurs when subtracting numbers of different signs
                // and the result has a different sign than the first operand
                overflow_flag = (a[7] != b[7]) && (result[7] != a[7]);
            end
            
            AND: begin
                result = a & b;
            end
            
            OR: begin
                result = a | b;
            end
            
            XOR: begin
                result = a ^ b;
            end
            
            NOT: begin
                result = ~a;
            end
            
            SHL: begin
                result = a << b[2:0]; // Use only lower 3 bits of B for shift amount
                // Carry is the last bit shifted out
                if (b[2:0] > 0)
                    carry_flag = (b[2:0] > 7) ? 0 : a[8-b[2:0]];
            end
            
            SHR: begin
                result = a >> b[2:0]; // Use only lower 3 bits of B for shift amount
                // Carry is the last bit shifted out
                if (b[2:0] > 0)
                    carry_flag = (b[2:0] > 7) ? 0 : a[b[2:0]-1];
            end
            
            CMPEQ: begin
                result = (a == b) ? 8'h01 : 8'h00;
            end
            
            CMPLT: begin
                result = ($signed(a) < $signed(b)) ? 8'h01 : 8'h00;
            end
            
            CMPLE: begin
                result = ($signed(a) <= $signed(b)) ? 8'h01 : 8'h00;
            end
            
            MUL: begin
                mul_temp = a * b;
                result = mul_temp[7:0];
                // Carry flag if upper bits are non-zero
                carry_flag = |mul_temp[15:8];
                // No defined overflow for multiplication in this ALU
            end
            
            default: begin
                result = 8'h00;
            end
        endcase
        
        // Set zero flag if result is zero
        zero_flag = (result == 8'h00);
    end

endmodule

project_2/alu/alu-test.v
`timescale 1ns/1ps

module alu_tb();
    // Test signals
    reg [7:0] a;
    reg [7:0] b;
    reg [3:0] op_code;
    wire [7:0] result;
    wire zero_flag;
    wire carry_flag;
    wire overflow_flag;
    
    // Instantiate the ALU
    alu dut(
        .a(a),
        .b(b),
        .op_code(op_code),
        .result(result),
        .zero_flag(zero_flag),
        .carry_flag(carry_flag),
        .overflow_flag(overflow_flag)
    );
    
    // Helper tasks
    task display_result;
        input [7:0] expected_result;
        input expected_zero;
        input expected_carry;
        input expected_overflow;
        begin
            #1; // Wait for signals to propagate
            
            $display("Operation: %b, A: %d, B: %d", op_code, a, b);
            $display("Result: %d (Expected: %d)", result, expected_result);
            $display("Zero Flag: %b (Expected: %b)", zero_flag, expected_zero);
            $display("Carry Flag: %b (Expected: %b)", carry_flag, expected_carry);
            $display("Overflow Flag: %b (Expected: %b)", overflow_flag, expected_overflow);
            
            if (result !== expected_result || zero_flag !== expected_zero || 
                carry_flag !== expected_carry || overflow_flag !== expected_overflow) begin
                $display("TEST FAILED!");
            end else begin
                $display("Test passed.");
            end
            
            $display("---------------------------");
        end
    endtask
    
    // Test stimulus
    initial begin
        $display("Starting ALU Testbench");
        
        // Test addition
        a = 8'd10; b = 8'd20; op_code = 4'b0000;
        #10 display_result(8'd30, 0, 0, 0);
        
        // Test addition with carry
        a = 8'd200; b = 8'd100; op_code = 4'b0000;
        #10 display_result(8'd44, 0, 1, 0); // 300 % 256 = 44, with carry
        
        // Test addition with overflow
        a = 8'd100; b = 8'd100; op_code = 4'b0000;
        #10 display_result(8'd200, 0, 0, 0);
        
        a = 8'h7F; b = 8'h01; op_code = 4'b0000; // 127 + 1 = 128 (overflow)
        #10 display_result(8'h80, 0, 0, 1);
        
        // Test subtraction
        a = 8'd50; b = 8'd20; op_code = 4'b0001;
        #10 display_result(8'd30, 0, 0, 0);
        
        // Test subtraction with borrow
        a = 8'd10; b = 8'd20; op_code = 4'b0001;
        #10 display_result(8'd246, 0, 1, 0); // -10 = 246 in two's complement
        
        // Test subtraction with overflow
        a = 8'h80; b = 8'h01; op_code = 4'b0001; // -128 - 1 = -129 (overflow)
        #10 display_result(8'h7F, 0, 1, 1);
        
        // Test logical operations
        a = 8'hAA; b = 8'h55; op_code = 4'b0010; // AND
        #10 display_result(8'h00, 1, 0, 0);
        
        a = 8'hAA; b = 8'h55; op_code = 4'b0011; // OR
        #10 display_result(8'hFF, 0, 0, 0);
        
        a = 8'hAA; b = 8'h55; op_code = 4'b0100; // XOR
        #10 display_result(8'hFF, 0, 0, 0);
        
        a = 8'hAA; b = 8'h00; op_code = 4'b0101; // NOT
        #10 display_result(8'h55, 0, 0, 0);
        
        // Test shifts
        a = 8'h01; b = 8'h03; op_code = 4'b0110; // SHL
        #10 display_result(8'h08, 0, 0, 0);
        
        a = 8'h80; b = 8'h03; op_code = 4'b0111; // SHR
        #10 display_result(8'h10, 0, 0, 0);
        
        // Test comparisons
        a = 8'd10; b = 8'd10; op_code = 4'b1000; // CMPEQ
        #10 display_result(8'h01, 0, 0, 0);
        
        a = 8'd5; b = 8'd10; op_code = 4'b1001; // CMPLT
        #10 display_result(8'h01, 0, 0, 0);
        
        a = 8'd10; b = 8'd10; op_code = 4'b1010; // CMPLE
        #10 display_result(8'h01, 0, 0, 0);
        
        // Test multiplication
        a = 8'd10; b = 8'd5; op_code = 4'b1011; // MUL
        #10 display_result(8'd50, 0, 0, 0);
        
        a = 8'd20; b = 8'd20; op_code = 4'b1011; // MUL with carry
        #10 display_result(8'd144, 0, 1, 0); // 400 % 256 = 144, with carry
        
        $display("ALU Testbench Complete");
        $finish;
    end
    
    // GTKWave dump
    initial begin
        $dumpfile("alu_tb.vcd");
        $dumpvars(0, alu_tb);
    end

endmodule

project_2/alu/alu_tb.vcd
$date
	Sun Mar 23 00:04:51 2025
$end
$version
	Icarus Verilog
$end
$timescale
	1ps
$end
$scope module alu_tb $end
$var wire 1 ! zero_flag $end
$var wire 8 " result [7:0] $end
$var wire 1 # overflow_flag $end
$var wire 1 $ carry_flag $end
$var reg 8 % a [7:0] $end
$var reg 8 & b [7:0] $end
$var reg 4 ' op_code [3:0] $end
$scope module dut $end
$var wire 8 ( a [7:0] $end
$var wire 8 ) b [7:0] $end
$var wire 4 * op_code [3:0] $end
$var parameter 4 + ADD $end
$var parameter 4 , AND $end
$var parameter 4 - CMPEQ $end
$var parameter 4 . CMPLE $end
$var parameter 4 / CMPLT $end
$var parameter 4 0 MUL $end
$var parameter 4 1 NOT $end
$var parameter 4 2 OR $end
$var parameter 4 3 SHL $end
$var parameter 4 4 SHR $end
$var parameter 4 5 SUB $end
$var parameter 4 6 XOR $end
$var reg 1 $ carry_flag $end
$var reg 16 7 mul_temp [15:0] $end
$var reg 1 # overflow_flag $end
$var reg 8 8 result [7:0] $end
$var reg 9 9 temp [8:0] $end
$var reg 1 ! zero_flag $end
$upscope $end
$scope task display_result $end
$var reg 1 : expected_carry $end
$var reg 1 ; expected_overflow $end
$var reg 8 < expected_result [7:0] $end
$var reg 1 = expected_zero $end
$upscope $end
$upscope $end
$enddefinitions $end
$comment Show the parameter values. $end
$dumpall
b100 6
b1 5
b111 4
b110 3
b11 2
b101 1
b1011 0
b1001 /
b1010 .
b1000 -
b10 ,
b0 +
$end
#0
$dumpvars
x=
bx <
x;
x:
b11110 9
b11110 8
bx 7
b0 *
b10100 )
b1010 (
b0 '
b10100 &
b1010 %
0$
0#
b11110 "
0!
$end
#10000
0;
0:
0=
b11110 <
#11000
1$
b101100 "
b101100 8
b100101100 9
b1100100 &
b1100100 )
b11001000 %
b11001000 (
#21000
1:
b101100 <
#22000
1#
b11001000 "
b11001000 8
b11001000 9
0$
b1100100 %
b1100100 (
#32000
0:
b11001000 <
#33000
b10000000 "
b10000000 8
b10000000 9
1#
b1 &
b1 )
b1111111 %
b1111111 (
#43000
1;
b10000000 <
#44000
b11110 "
b11110 8
b11110 9
0#
b1 '
b1 *
b10100 &
b10100 )
b110010 %
b110010 (
#54000
0;
b11110 <
#55000
1$
b11110110 "
b11110110 8
b111110110 9
b1010 %
b1010 (
#65000
1:
b11110110 <
#66000
1#
b1111111 "
b1111111 8
b1111111 9
0$
b1 &
b1 )
b10000000 %
b10000000 (
#76000
1;
b1111111 <
#77000
1!
b0 "
b0 8
0#
b10 '
b10 *
b1010101 &
b1010101 )
b10101010 %
b10101010 (
#87000
0;
0:
1=
b0 <
#88000
b11111111 "
b11111111 8
0!
b11 '
b11 *
#98000
0=
b11111111 <
#99000
b100 '
b100 *
#110000
b1010101 "
b1010101 8
b101 '
b101 *
b0 &
b0 )
#120000
b1010101 <
#121000
b1000 "
b1000 8
b110 '
b110 *
b11 &
b11 )
b1 %
b1 (
#131000
b1000 <
#132000
b10000 "
b10000 8
b111 '
b111 *
b10000000 %
b10000000 (
#142000
b10000 <
#143000
b1 "
b1 8
b1000 '
b1000 *
b1010 &
b1010 )
b1010 %
b1010 (
#153000
b1 <
#154000
b1001 '
b1001 *
b101 %
b101 (
#165000
b1010 '
b1010 *
b1010 %
b1010 (
#176000
b110010 "
b110010 8
b110010 7
b1011 '
b1011 *
b101 &
b101 )
#186000
b110010 <
#187000
1$
b10010000 "
b10010000 8
b110010000 7
b10100 &
b10100 )
b10100 %
b10100 (
#197000
1:
b10010000 <
